ginpipe/__init__.py
ginpipe/core.py
ginpipe/run.py
ginpipe-0.0.2.dist-info/METADATA
ginpipe-0.0.2.dist-info/WHEEL
ginpipe-0.0.2.dist-info/entry_points.txt
ginpipe-0.0.2.dist-info/top_level.txt
ginpipe-0.0.2.dist-info/RECORD
